lerobotlab/__init__.py
lerobotlab/cli.py
lerobotlab/convert.py
lerobotlab/download.py
lerobotlab/droid_conversion.py
lerobotlab/vjepa2_ac_conversion.py
lerobotlab-0.1.6.dist-info/METADATA
lerobotlab-0.1.6.dist-info/WHEEL
lerobotlab-0.1.6.dist-info/entry_points.txt
lerobotlab-0.1.6.dist-info/top_level.txt
lerobotlab-0.1.6.dist-info/RECORD
