Metadata-Version: 2.4
Name: lerobotlab
Version: 0.1.6
Summary: CLI tool for processing robot dataset selections from lerobotlab.com
Author-email: newtechmitch <pipy@lerobotlab.com>
License: Apache-2.0
Project-URL: Homepage, https://github.com/newtechmitch/lerobotlab-tools
Project-URL: Repository, https://github.com/newtechmitch/lerobotlab-tools
Project-URL: Issues, https://github.com/newtechmitch/lerobotlab-tools/issues
Keywords: robotics,datasets,cli,machine-learning
Classifier: Development Status :: 3 - Alpha
Classifier: Intended Audience :: Developers
Classifier: Intended Audience :: Science/Research
Classifier: License :: OSI Approved :: Apache Software License
Classifier: Operating System :: OS Independent
Classifier: Programming Language :: Python :: 3
Classifier: Programming Language :: Python :: 3.10
Classifier: Programming Language :: Python :: 3.11
Classifier: Programming Language :: Python :: 3.12
Classifier: Topic :: Scientific/Engineering :: Artificial Intelligence
Classifier: Topic :: Software Development :: Libraries :: Python Modules
Requires-Python: >=3.10
Requires-Dist: h5py>=3.0.0
Requires-Dist: pandas>=1.0.0
Requires-Dist: numpy>=1.19.0
Requires-Dist: lerobot>=0.3.2
